cricketlivescore/__init__.py
cricketlivescore/score.py
cricketlivescore-1.1.2.data/scripts/cricls
cricketlivescore-1.1.2.dist-info/DESCRIPTION.rst
cricketlivescore-1.1.2.dist-info/METADATA
cricketlivescore-1.1.2.dist-info/RECORD
cricketlivescore-1.1.2.dist-info/WHEEL
cricketlivescore-1.1.2.dist-info/metadata.json
cricketlivescore-1.1.2.dist-info/top_level.txt
