Metadata-Version: 2.0
Name: cricketlivescore
Version: 1.1.2
Summary: Get live cricket scores
Home-page: http://github.com/appi147/cricketlivescore
Author: Arpit Choudhary
Author-email: arpitkumar147@gmail.com
License: MIT
Keywords: cricket live score
Platform: UNKNOWN
Requires-Dist: feedparser
